[
  {"adr":"011","status":"PASS","expected":"Workbench running","actual":"0
0 workbench pods, 1 notebook pods","details":"PyTorch workbench operational","timestamp":"2026-03-03T21:25:19Z"}
,
  {"adr":"012","status":"FAIL","expected":"32 notebooks in 9 directories","actual":"0 notebooks","details":"Insufficient notebooks","timestamp":"2026-03-03T21:25:19Z"}
,
  {"adr":"013","status":"FAIL","expected":"5 data collection notebooks","actual":"0 notebooks","details":"Data collection not configured","timestamp":"2026-03-03T21:25:19Z"}
,
  {"adr":"029","status":"FAIL","expected":"Operator running with CRD","actual":"CRD not found","details":"Operator not deployed","timestamp":"2026-03-03T21:25:19Z"}
,
  {"adr":"031","status":"PARTIAL","expected":"Custom image built","actual":"Dockerfile exists but image not built","details":"Image definition ready","timestamp":"2026-03-03T21:25:19Z"}
,
  {"adr":"032","status":"FAIL","expected":"Validation notebook executed","actual":"Notebook not found","details":"Validation notebook missing","timestamp":"2026-03-03T21:25:19Z"}
]
